rocmgid/__init__.py
rocmgid/cli.py
rocmgid-0.1.dist-info/METADATA
rocmgid-0.1.dist-info/WHEEL
rocmgid-0.1.dist-info/entry_points.txt
rocmgid-0.1.dist-info/top_level.txt
rocmgid-0.1.dist-info/RECORD
